nest_tree/__init__.py
nest_tree/tree.py
nest_tree-0.1.1.dist-info/licenses/LICENSE
nest_tree-0.1.1.dist-info/METADATA
nest_tree-0.1.1.dist-info/WHEEL
nest_tree-0.1.1.dist-info/top_level.txt
nest_tree-0.1.1.dist-info/RECORD
