Metadata-Version: 2.4
Name: nest-tree
Version: 0.1.1
Summary: A tool to print out the structure of nested Python dict and list, like the `tree` command line tool.
Author-email: Sibo Wang-Chen <sibo.wang@epfl.ch>
License: MIT
Project-URL: Homepage, https://github.com/sibocw/nest-tree
Classifier: Development Status :: 4 - Beta
Classifier: Intended Audience :: Developers
Classifier: License :: OSI Approved :: MIT License
Classifier: Programming Language :: Python :: 3
Classifier: Programming Language :: Python :: 3.7
Classifier: Programming Language :: Python :: 3.8
Classifier: Programming Language :: Python :: 3.9
Classifier: Programming Language :: Python :: 3.10
Classifier: Programming Language :: Python :: 3.11
Classifier: Programming Language :: Python :: 3.12
Requires-Python: >=3.7
License-File: LICENSE
Dynamic: license-file
